macun/__init__.py
macun/main.py
macun/utils.py
macun-1.31.dist-info/LICENSE
macun-1.31.dist-info/METADATA
macun-1.31.dist-info/WHEEL
macun-1.31.dist-info/entry_points.txt
macun-1.31.dist-info/top_level.txt
macun-1.31.dist-info/RECORD
