Metadata-Version: 2.2
Name: macun
Version: 1.31
Summary: MAACUUUUN
Author-email: Tuğra Şen <sentugraa@gmail.com>
License: MIT
Keywords: macun,python,project
Requires-Python: >=3.9
License-File: LICENSE
Requires-Dist: colorama
Requires-Dist: g4f[all]<0.5.0.0,>=0.4.6.1
